MANIFEST.in
README.md
setup.py
structure.yml
types.yml
fam_parser.egg-info/PKG-INFO
fam_parser.egg-info/SOURCES.txt
fam_parser.egg-info/dependency_links.txt
fam_parser.egg-info/entry_points.txt
fam_parser.egg-info/requires.txt
fam_parser.egg-info/top_level.txt
python/__init__.py
python/cli.py
python/fam_parser.py
python/structure.yml
python/types.yml