Metadata-Version: 1.0
Name: fam-parser
Version: 0.0.19
Summary: FAM file parser
Home-page: https://git.lumc.nl/pedigree/fam-parser
Author: Jeroen F.J. Laros
Author-email: J.F.J.Laros@lumc.nl
License: MIT License
Platform: any
